[
  {
    "skill_id": "beginner-wheeling-forward",
    "title": "Wheeling Forward",
    "level": "beginner",
    "total_steps": 4
  },
  {
    "skill_id": "beginner-wheeling-backward",
    "title": "Wheeling Backward",
    "level": "beginner",
    "total_steps": 4
  },
  {
    "skill_id": "beginner-turn-on-spot",
    "title": "Turning on the Spot",
    "level": "beginner",
    "total_steps": 3
  },
  {
    "skill_id": "beginner-turn-forward",
    "title": "Turning while Wheeling Forward",
    "level": "beginner",
    "total_steps": 3
  },
  {
    "skill_id": "beginner-turn-backward",
    "title": "Turning while Wheeling Backward",
    "level": "beginner",
    "total_steps": 3
  },
  {
    "skill_id": "intermediate-drag-turns",
    "title": "Drag Turns",
    "level": "intermediate",
    "total_steps": 4
  },
  {
    "skill_id": "intermediate-push-off-turns",
    "title": "Push-off Turns",
    "level": "intermediate",
    "total_steps": 3
  },
  {
    "skill_id": "intermediate-ramps-up",
    "title": "Wheeling Up Ramps",
    "level": "intermediate",
    "total_steps": 3
  },
  {
    "skill_id": "intermediate-ramps-down",
    "title": "Wheeling Down Ramps",
    "level": "intermediate",
    "total_steps": 3
  },
  {
    "skill_id": "intermediate-side-slopes",
    "title": "Wheeling on Side Slopes",
    "level": "intermediate",
    "total_steps": 3
  },
  {
    "skill_id": "intermediate-shuffling-sideways",
    "title": "Shuffling Sideways",
    "level": "intermediate",
    "total_steps": 3
  },
  {
    "skill_id": "intermediate-pick-object",
    "title": "Picking an Object off the Floor",
    "level": "intermediate",
    "total_steps": 3
  },
  {
    "skill_id": "intermediate-popping-casters",
    "title": "Popping Casters",
    "level": "intermediate",
    "total_steps": 3
  },
  {
    "skill_id": "intermediate-obstacles-thresholds",
    "title": "Wheeling over Obstacles (thresholds)",
    "level": "intermediate",
    "total_steps": 3
  },
  {
    "skill_id": "intermediate-soft-surfaces",
    "title": "Wheeling over Soft Surfaces",
    "level": "intermediate",
    "total_steps": 3
  },
  {
    "skill_id": "intermediate-doors-out",
    "title": "Using Doors that Swing Out",
    "level": "intermediate",
    "total_steps": 3
  },
  {
    "skill_id": "intermediate-doors-in",
    "title": "Using Doors that Swing In",
    "level": "intermediate",
    "total_steps": 3
  },
  {
    "skill_id": "intermediate-avoid-collisions",
    "title": "Avoiding Collisions (quick stop / quick turn)",
    "level": "intermediate",
    "total_steps": 2
  },
  {
    "skill_id": "intermediate-curb-up-help",
    "title": "Bumping Up a Curb with Help",
    "level": "intermediate",
    "total_steps": 3
  },
  {
    "skill_id": "intermediate-curb-down-help",
    "title": "Bumping Down a Curb with Help",
    "level": "intermediate",
    "total_steps": 3
  },
  {
    "skill_id": "intermediate-stairs-3-helpers",
    "title": "Bumping Up/Down Stairs with 3 Helpers",
    "level": "intermediate",
    "total_steps": 3
  },
  {
    "skill_id": "advanced-curb-up",
    "title": "Getting Up Curbs (solo pop + roll up)",
    "level": "advanced",
    "total_steps": 4
  },
  {
    "skill_id": "advanced-curb-down-backwards",
    "title": "Getting Down Curbs (backwards)",
    "level": "advanced",
    "total_steps": 3
  },
  {
    "skill_id": "advanced-holding-wheelie",
    "title": "Holding a Wheelie",
    "level": "advanced",
    "total_steps": 4
  },
  {
    "skill_id": "emergency-stairs-2-helpers",
    "title": "Bumping Stairs with 2 Helpers (emergency)",
    "level": "emergency",
    "total_steps": 3
  }
]